[
 {
  "contributed_translation_doctype_name": null,
  "docstatus": 0,
  "doctype": "Translation",
  "language": "es",
  "modified": "2020-08-14 10:30:46.442200",
  "name": "42bb909439",
  "parent": null,
  "parentfield": null,
  "parenttype": null,
  "source_name": "Consumable Acquisition Record",
  "status": "Saved",
  "target_name": "Constancia de Adquisici\u00f3n de Insumos"
 },
 {
  "contributed_translation_doctype_name": null,
  "docstatus": 0,
  "doctype": "Translation",
  "language": "es",
  "modified": "2020-08-14 10:30:46.633275",
  "name": "a4b3f45346",
  "parent": null,
  "parentfield": null,
  "parenttype": null,
  "source_name": "Date of Retention",
  "status": "Saved",
  "target_name": "Fecha de Retenci\u00f3n"
 },
 {
  "contributed_translation_doctype_name": null,
  "docstatus": 0,
  "doctype": "Translation",
  "language": "es",
  "modified": "2020-08-14 10:30:46.712275",
  "name": "7ae1e9f0d6",
  "parent": null,
  "parentfield": null,
  "parenttype": null,
  "source_name": "Declaration Date",
  "status": "Saved",
  "target_name": "Fecha de la Declaraci\u00f3n"
 },
 {
  "contributed_translation_doctype_name": null,
  "docstatus": 0,
  "doctype": "Translation",
  "language": "es",
  "modified": "2020-08-14 10:30:46.757652",
  "name": "4d755e06a2",
  "parent": null,
  "parentfield": null,
  "parenttype": null,
  "source_name": "Documents In Declaration",
  "status": "Saved",
  "target_name": "Documentos incluidos en la declaraci\u00f3n"
 },
 {
  "contributed_translation_doctype_name": null,
  "docstatus": 0,
  "doctype": "Translation",
  "language": "en",
  "modified": "2020-08-14 10:30:46.929151",
  "name": "c0bab1b319",
  "parent": null,
  "parentfield": null,
  "parenttype": null,
  "source_name": "Es Factura Especial",
  "status": "Saved",
  "target_name": "Is Special Invoice"
 },
 {
  "contributed_translation_doctype_name": null,
  "docstatus": 0,
  "doctype": "Translation",
  "language": "es",
  "modified": "2020-08-14 10:30:47.352112",
  "name": "278fe5872c",
  "parent": null,
  "parentfield": null,
  "parenttype": null,
  "source_name": "Income Tax Retentions",
  "status": "Saved",
  "target_name": "Retenciones de ISR"
 },
 {
  "contributed_translation_doctype_name": null,
  "docstatus": 0,
  "doctype": "Translation",
  "language": "es",
  "modified": "2020-08-14 10:30:47.370520",
  "name": "5e8926f1cd",
  "parent": null,
  "parentfield": null,
  "parenttype": null,
  "source_name": "Invoice Date",
  "status": "Saved",
  "target_name": "Fecha de la Factura"
 },
 {
  "contributed_translation_doctype_name": null,
  "docstatus": 0,
  "doctype": "Translation",
  "language": "es",
  "modified": "2020-08-14 10:30:47.392949",
  "name": "3007f6c137",
  "parent": null,
  "parentfield": null,
  "parenttype": null,
  "source_name": "Invoice Number",
  "status": "Saved",
  "target_name": "Numero de Factura"
 },
 {
  "contributed_translation_doctype_name": null,
  "docstatus": 0,
  "doctype": "Translation",
  "language": "es",
  "modified": "2020-08-14 10:30:47.413114",
  "name": "60be72f9b3",
  "parent": null,
  "parentfield": null,
  "parenttype": null,
  "source_name": "Invoice Total",
  "status": "Saved",
  "target_name": "Total de la Factura"
 },
 {
  "contributed_translation_doctype_name": null,
  "docstatus": 0,
  "doctype": "Translation",
  "language": "es",
  "modified": "2020-08-14 10:30:47.432336",
  "name": "57f146ef5a",
  "parent": null,
  "parentfield": null,
  "parenttype": null,
  "source_name": "Is Special Invoice",
  "status": "Saved",
  "target_name": "Es Factura Especial"
 },
 {
  "contributed_translation_doctype_name": null,
  "docstatus": 0,
  "doctype": "Translation",
  "language": "es",
  "modified": "2020-08-14 10:30:48.179168",
  "name": "4f27d8f163",
  "parent": null,
  "parentfield": null,
  "parenttype": null,
  "source_name": "Public Writ",
  "status": "Saved",
  "target_name": "Escritura P\u00fablica"
 },
 {
  "contributed_translation_doctype_name": null,
  "docstatus": 0,
  "doctype": "Translation",
  "language": "es",
  "modified": "2020-08-14 10:30:48.218050",
  "name": "b93e7f46d3",
  "parent": null,
  "parentfield": null,
  "parenttype": null,
  "source_name": "Purchase Ledger Page Number",
  "status": "Saved",
  "target_name": "Numero de Folio Libro de Compras"
 },
 {
  "contributed_translation_doctype_name": null,
  "docstatus": 0,
  "doctype": "Translation",
  "language": "es",
  "modified": "2020-08-14 10:30:48.436932",
  "name": "ce0e4af507",
  "parent": null,
  "parentfield": null,
  "parenttype": null,
  "source_name": "Retention Confirmation Number",
  "status": "Saved",
  "target_name": "Constancia de Retencion"
 },
 {
  "contributed_translation_doctype_name": null,
  "docstatus": 0,
  "doctype": "Translation",
  "language": "es",
  "modified": "2020-08-14 10:30:48.483083",
  "name": "a3688ed09e",
  "parent": null,
  "parentfield": null,
  "parenttype": null,
  "source_name": "SAT Form",
  "status": "Saved",
  "target_name": "Formulario SAT"
 },
 {
  "contributed_translation_doctype_name": null,
  "docstatus": 0,
  "doctype": "Translation",
  "language": "es",
  "modified": "2020-08-14 10:30:48.512922",
  "name": "9793bb9496",
  "parent": null,
  "parentfield": null,
  "parenttype": null,
  "source_name": "Sales Ledger Page Number",
  "status": "Saved",
  "target_name": "Numero de Folio Libro de Ventas"
 },
 {
  "contributed_translation_doctype_name": null,
  "docstatus": 0,
  "doctype": "Translation",
  "language": "es",
  "modified": "2020-08-14 10:30:48.828281",
  "name": "720c3c8d97",
  "parent": null,
  "parentfield": null,
  "parenttype": null,
  "source_name": "Tax Category Group",
  "status": "Saved",
  "target_name": "Grupos de Categor\u00eda de Impuestos"
 },
 {
  "contributed_translation_doctype_name": null,
  "docstatus": 0,
  "doctype": "Translation",
  "language": "es",
  "modified": "2020-08-14 10:30:48.855661",
  "name": "5d57b692d4",
  "parent": null,
  "parentfield": null,
  "parenttype": null,
  "source_name": "Tax ID",
  "status": "Saved",
  "target_name": "NIT"
 },
 {
  "contributed_translation_doctype_name": null,
  "docstatus": 0,
  "doctype": "Translation",
  "language": "es",
  "modified": "2020-08-14 10:30:48.968928",
  "name": "68bbf1526e",
  "parent": null,
  "parentfield": null,
  "parenttype": null,
  "source_name": "Unique Customs Declaration",
  "status": "Saved",
  "target_name": "Declaracion Unica Aduanera"
 },
 {
  "contributed_translation_doctype_name": null,
  "docstatus": 0,
  "doctype": "Translation",
  "language": "es",
  "modified": "2020-08-14 10:30:49.106339",
  "name": "3eb7d3bbe7",
  "parent": null,
  "parentfield": null,
  "parenttype": null,
  "source_name": "VAT Exemption Record",
  "status": "Saved",
  "target_name": "Constancia de Exenci\u00f3n de IVA"
 },
 {
  "contributed_translation_doctype_name": null,
  "docstatus": 0,
  "doctype": "Translation",
  "language": "es",
  "modified": "2020-08-14 10:30:49.135188",
  "name": "0c237c525e",
  "parent": null,
  "parentfield": null,
  "parenttype": null,
  "source_name": "VAT Retentions",
  "status": "Saved",
  "target_name": "Retenciones de IVA"
 },
 {
  "contributed_translation_doctype_name": null,
  "docstatus": 0,
  "doctype": "Translation",
  "language": "es",
  "modified": "2020-08-14 10:30:49.167275",
  "name": "38f0f154d6",
  "parent": null,
  "parentfield": null,
  "parenttype": null,
  "source_name": "VAT and Income Tax Retention Report",
  "status": "Saved",
  "target_name": "Reporte de Retenciones IVA e ISR"
 }
]